setup.py
src/infi/__init__.py
src/infi.nose_logbook.egg-info/PKG-INFO
src/infi.nose_logbook.egg-info/SOURCES.txt
src/infi.nose_logbook.egg-info/dependency_links.txt
src/infi.nose_logbook.egg-info/entry_points.txt
src/infi.nose_logbook.egg-info/namespace_packages.txt
src/infi.nose_logbook.egg-info/not-zip-safe
src/infi.nose_logbook.egg-info/requires.txt
src/infi.nose_logbook.egg-info/top_level.txt
src/infi/nose_logbook/__init__.py
src/infi/nose_logbook/__version__.py