Metadata-Version: 1.1
Name: infi.nose_logbook
Version: 1.0
Summary: Logbook integration for Nose
Home-page: https://github.com/Infinidat/infi.nose_logbook
Author: Guy Rozendorn
Author-email: guy@rzn.co.il
License: PSF
Platform: UNKNOWN
Classifier: Intended Audience :: Developers
Classifier: Intended Audience :: System Administrators
Classifier: License :: OSI Approved :: Python Software Foundation License
Classifier: Operating System :: OS Independent
Classifier: Programming Language :: Python
Classifier: Topic :: Software Development :: Libraries :: Python Modules
